CHANGES.rst
LICENSE
MANIFEST.in
README.rst
TODO.rst
setup.py
mmstats/__init__.py
mmstats/_libgettid.c
mmstats/_mmap.py
mmstats/clean.py
mmstats/defaults.py
mmstats/fields.py
mmstats/libgettid.py
mmstats/mmash.py
mmstats/mmash_settings.py
mmstats/models.py
mmstats/pollstats.py
mmstats/reader.py
mmstats/slurpstats.py
mmstats.egg-info/PKG-INFO
mmstats.egg-info/SOURCES.txt
mmstats.egg-info/dependency_links.txt
mmstats.egg-info/entry_points.txt
mmstats.egg-info/not-zip-safe
mmstats.egg-info/requires.txt
mmstats.egg-info/top_level.txt
mmstats/static/base.css
mmstats/static/jquery.flot.js
mmstats/static/jquery.js
mmstats/templates/graph.html
mmstats/templates/index.html