Metadata-Version: 1.0
Name: mmstats
Version: 0.6.2
Summary: Stat, metric, and diagnostic publishing and consuming tools
Home-page: https://github.com/schmichael/mmstats
Author: Michael Schurter
Author-email: m@schmichael.com
License: APLv2
Platform: UNKNOWN
Classifier: License :: OSI Approved :: Apache Software License
